Metadata-Version: 1.1
Name: hadmlservices
Version: 1.0.15
Summary: HAD ML Services
Home-page: https://h7f8ovvjxk.execute-api.us-east-1.amazonaws.com/beta/index.html#/
Author: Sensing and Perception Team
Author-email: vladimir.shestak@here.com
License: Property of HERE
Keywords: HAD API Model Runtime
Platform: UNKNOWN
Classifier: Development Status :: 3 - Alpha
Classifier: Intended Audience :: Developers
Classifier: Topic :: Software Development :: Build Tools
Classifier: License :: OSI Approved :: MIT License
Classifier: Programming Language :: Python :: 2.7
